eid_image_extractor/__init__.py
eid_image_extractor/__main__.py
eid_image_extractor/eid.py
eid_image_extractor-1.0.2.dist-info/licenses/LICENSE
eid_image_extractor-1.0.2.dist-info/METADATA
eid_image_extractor-1.0.2.dist-info/WHEEL
eid_image_extractor-1.0.2.dist-info/entry_points.txt
eid_image_extractor-1.0.2.dist-info/top_level.txt
eid_image_extractor-1.0.2.dist-info/RECORD
