Metadata-Version: 2.4
Name: eid-image-extractor
Version: 1.0.2
Summary: A simple python script to extract the image from a Belgian E-ID card 
Author-email: Bram Oosterlynck <bram.oosterlynck@gmail.com>
License:                     GNU GENERAL PUBLIC LICENSE
Project-URL: Homepage, https://github.com/boosterl/eid-image-extractor
Keywords: identity,eid,beid
Classifier: License :: OSI Approved :: GNU General Public License v3 (GPLv3)
Classifier: Intended Audience :: Developers
Classifier: Programming Language :: Python :: 3
Classifier: Programming Language :: Python :: 3.8
Classifier: Programming Language :: Python :: 3.9
Classifier: Programming Language :: Python :: 3.10
Classifier: Programming Language :: Python :: 3.11
Classifier: Programming Language :: Python :: 3.12
Classifier: Programming Language :: Python :: 3.13
License-File: LICENSE
Requires-Dist: click>=8.3.0
Requires-Dist: eidreader>=1.0.8
Dynamic: license-file
